olot/__init__.py
olot/backend/oras_cp.py
olot/backend/skopeo.py
olot/basics.py
olot/cli.py
olot/dockerdist/convert.py
olot/modelpack/__init__.py
olot/modelpack/const.py
olot/modelpack/model_config.py
olot/oci/oci_common.py
olot/oci/oci_config.py
olot/oci/oci_defs.py
olot/oci/oci_defs_descriptor.py
olot/oci/oci_image_index.py
olot/oci/oci_image_layout.py
olot/oci/oci_image_manifest.py
olot/oci_artifact.py
olot/utils/files.py
olot/utils/types.py
olot-0.1.11.dist-info/METADATA
olot-0.1.11.dist-info/WHEEL
olot-0.1.11.dist-info/entry_points.txt
olot-0.1.11.dist-info/licenses/LICENSE
olot-0.1.11.dist-info/RECORD
