Metadata-Version: 2.4
Name: olot
Version: 0.1.11
Summary: oci layers on top
License-File: LICENSE
Author: tarilabs
Author-email: matteo.mortari@gmail.com
Requires-Python: >=3.9,<4.0
Classifier: Programming Language :: Python :: 3
Classifier: Programming Language :: Python :: 3.9
Classifier: Programming Language :: Python :: 3.10
Classifier: Programming Language :: Python :: 3.11
Classifier: Programming Language :: Python :: 3.12
Classifier: Programming Language :: Python :: 3.13
Classifier: Programming Language :: Python :: 3.14
Requires-Dist: click (>=8.1.7,<9.0.0)
Requires-Dist: pydantic (>=2.10.3,<3.0.0)
